helptrain/__init__.py
helptrain/mylib.py
helptrain-0.0.9.dist-info/LICENSE.txt
helptrain-0.0.9.dist-info/METADATA
helptrain-0.0.9.dist-info/WHEEL
helptrain-0.0.9.dist-info/top_level.txt
helptrain-0.0.9.dist-info/RECORD
