Metadata-Version: 2.1
Name: helptrain
Version: 0.0.9
Summary: help to train your network based on pytorch
Author: SXQ
Author-email: xiaoqiang.s@outlook.com
Classifier: Programming Language :: Python :: 3
Classifier: License :: OSI Approved :: MIT License
Classifier: Operating System :: Microsoft :: Windows :: Windows 10
Requires-Python: >=3.6
License-File: LICENSE.txt
